odoo8_addon_l10n_ch_dta_base_transaction_id-8.0.1.0.0.99.dev3-py2.7-nspkg.pth
odoo8_addon_l10n_ch_dta_base_transaction_id-8.0.1.0.0.99.dev3.dist-info/METADATA
odoo8_addon_l10n_ch_dta_base_transaction_id-8.0.1.0.0.99.dev3.dist-info/RECORD
odoo8_addon_l10n_ch_dta_base_transaction_id-8.0.1.0.0.99.dev3.dist-info/WHEEL
odoo8_addon_l10n_ch_dta_base_transaction_id-8.0.1.0.0.99.dev3.dist-info/namespace_packages.txt
odoo8_addon_l10n_ch_dta_base_transaction_id-8.0.1.0.0.99.dev3.dist-info/top_level.txt
odoo_addons/l10n_ch_dta_base_transaction_id/__init__.py
odoo_addons/l10n_ch_dta_base_transaction_id/__openerp__.py
odoo_addons/l10n_ch_dta_base_transaction_id/static/description/icon.png
odoo_addons/l10n_ch_dta_base_transaction_id/wizard/__init__.py
odoo_addons/l10n_ch_dta_base_transaction_id/wizard/create_dta.py
